LICENSE
README.md
setup.py
PyWin10UI.egg-info/PKG-INFO
PyWin10UI.egg-info/SOURCES.txt
PyWin10UI.egg-info/dependency_links.txt
PyWin10UI.egg-info/requires.txt
PyWin10UI.egg-info/top_level.txt
pywin10ui/__init__.py
pywin10ui/demo.py