Metadata-Version: 2.1
Name: PyWin10UI
Version: 0.1.0
Summary: 基于Pygame的UI模块,支持模块以外的pygame组件
Home-page: https://github.com/bytfr/pywin10ui
Author: bytfr 啃竹子
Author-email: 2678509244@qq.com
License: MIT
Platform: UNKNOWN
License-File: LICENSE
